nlbsg/__about__.py
nlbsg/__init__.py
nlbsg/__version__.py
nlbsg/_factories.py
nlbsg/catalog.py
nlbsg/catalogue.py
nlbsg/constants.py
nlbsg/types.py
nlbsg-0.5.0.dist-info/LICENSE
nlbsg-0.5.0.dist-info/METADATA
nlbsg-0.5.0.dist-info/WHEEL
nlbsg-0.5.0.dist-info/top_level.txt
nlbsg-0.5.0.dist-info/RECORD
