Metadata-Version: 2.1
Name: nlbsg
Version: 0.5.0
Summary: Python SDK for the NLB Open Web Services
Home-page: https://github.com/yi-jiayu/nlbsg
Author: Jiayu Yi
Author-email: yijiayu@gmail.com
License: MIT
Project-URL: Documentation, https://nlbsg.readthedocs.io/en/latest/
Project-URL: Source code, https://github.com/yi-jiayu/nlbsg
Project-URL: Builds, https://travis-ci.com/yi-jiayu/nlbsg
Project-URL: Coverage, https://codecov.io/gh/yi-jiayu/nlbsg
Platform: UNKNOWN
Classifier: Programming Language :: Python :: 3.7
Classifier: License :: OSI Approved :: MIT License
Classifier: Operating System :: OS Independent
Requires-Python: >=3.7
Requires-Dist: zeep
